<?xml version="1.0" encoding="utf-8" ?>
<dwsync>
<file name="class-forminator-addon-trello-exception.php.bin" server="access948077722.webspace-data.io" local="133182974980000000" remote="133182974980000000" Dst="1" />
<file name="class-forminator-addon-trello-form-hooks.php.bin" server="access948077722.webspace-data.io" local="133182974980000000" remote="133182974980000000" Dst="1" />
<file name="class-forminator-addon-trello-form-settings-exception.php.bin" server="access948077722.webspace-data.io" local="133182974980000000" remote="133182974980000000" Dst="1" />
<file name="class-forminator-addon-trello-form-settings.php.bin" server="access948077722.webspace-data.io" local="133182974980000000" remote="133182974980000000" Dst="1" />
<file name="class-forminator-addon-trello-poll-hooks.php.bin" server="access948077722.webspace-data.io" local="133182974980000000" remote="133182974980000000" Dst="1" />
<file name="class-forminator-addon-trello-poll-settings-exception.php.bin" server="access948077722.webspace-data.io" local="133182974980000000" remote="133182974980000000" Dst="1" />
<file name="class-forminator-addon-trello-poll-settings.php.bin" server="access948077722.webspace-data.io" local="133182974980000000" remote="133182974980000000" Dst="1" />
<file name="class-forminator-addon-trello-quiz-hooks.php.bin" server="access948077722.webspace-data.io" local="133182974980000000" remote="133182974980000000" Dst="1" />
<file name="class-forminator-addon-trello-quiz-settings-exception.php.bin" server="access948077722.webspace-data.io" local="133182974980000000" remote="133182974980000000" Dst="1" />
<file name="class-forminator-addon-trello-quiz-settings.php.bin" server="access948077722.webspace-data.io" local="133182974980000000" remote="133182974980000000" Dst="1" />
<file name="class-forminator-addon-trello.php.bin" server="access948077722.webspace-data.io" local="133182974980000000" remote="133182974980000000" Dst="1" />
<file name="trello.php.bin" server="access948077722.webspace-data.io" local="133182974980000000" remote="133182974980000000" Dst="1" />
</dwsync>